richviewsdk/__init__.py
richviewsdk-1.0.7.dist-info/METADATA
richviewsdk-1.0.7.dist-info/WHEEL
richviewsdk-1.0.7.dist-info/top_level.txt
richviewsdk-1.0.7.dist-info/RECORD
