Metadata-Version: 2.1
Name: richviewsdk
Version: 1.0.7
Summary: Package to interact with RichView API.
Home-page: https://therichview.com/
Author: Daniel Vecera
Author-email: daniel@therichview.com
License: UNKNOWN
Platform: UNKNOWN
Requires-Python: >=3.9
Requires-Dist: recordclass
Requires-Dist: pandas (>=1.2.0)
Requires-Dist: requests
Requires-Dist: shortuuid
Requires-Dist: mergedeep
